alphabetsoup/__init__.py
alphabetsoup/__main__.py
alphabetsoup/common.py
alphabetsoup/process_file.py
alphabetsoup/process_logs.py
alphabetsoup/version.py
alphabetsoup-0.5.3.dist-info/entry_points.txt
alphabetsoup-0.5.3.dist-info/LICENSE.txt
alphabetsoup-0.5.3.dist-info/WHEEL
alphabetsoup-0.5.3.dist-info/METADATA
alphabetsoup-0.5.3.dist-info/RECORD
