Metadata-Version: 2.1
Name: alphabetsoup
Version: 0.5.3
Summary: tile phylogenetic space with subtrees
Home-page: https://github.com/ncgr/alphabetsoup
License: BSD-3-Clause
Keywords: science,biology,bioinformatics,genomics,data science,phylogeny,protein,sequences,FASTA
Author: Joel Berendzen
Author-email: joelb@ncgr.org
Requires-Python: >=3.6.1,<4.0.0
Classifier: Development Status :: 5 - Production/Stable
Classifier: Environment :: Console
Classifier: Intended Audience :: Science/Research
Classifier: License :: OSI Approved :: BSD License
Classifier: Natural Language :: English
Classifier: Operating System :: OS Independent
Classifier: Programming Language :: Python :: 3
Classifier: Programming Language :: Python :: 3.6
Classifier: Programming Language :: Python :: 3.7
Classifier: Programming Language :: Python :: 3.8
Classifier: Programming Language :: Python :: 3.9
Classifier: Topic :: Scientific/Engineering :: Bio-Informatics
Requires-Dist: biopython (>=1.76,<2.0)
Requires-Dist: click (>=7.1.2,<8.0.0)
Requires-Dist: click_loguru (>=0.3.3,<0.4.0)
Requires-Dist: cloudpickle (>=1.4.1,<2.0.0)
Requires-Dist: dask[bag] (>=2.15.0,<3.0.0)
Requires-Dist: matplotlib (>=3.2.1,<4.0.0)
Requires-Dist: pandas (>=1.0.3,<2.0.0)
Requires-Dist: seaborn (>=0.10.1,<0.11.0)
Requires-Dist: toolz (>=0.10.0,<0.11.0)
Project-URL: Documentation, https://alphabetsoup.readthedocs.org
